secuscan/__init__.py
secuscan/__main__.py
secuscan/cli.py
secuscan/config/secuscan.yaml
secuscan/core/__init__.py
secuscan/core/config.py
secuscan/core/detection.py
secuscan/core/docker_manager.py
secuscan/core/engine.py
secuscan/core/exceptions.py
secuscan/reporting/reporter.py
secuscan/reporting/templates/report_template.html
secuscan/scanners/__init__.py
secuscan/scanners/base.py
secuscan/scanners/factory.py
secuscan/scanners/models.py
secuscan/scanners/secrets.py
secuscan/scanners/android/__init__.py
secuscan/scanners/android/mobsf_adapter.py
secuscan/scanners/android/scanner.py
secuscan/scanners/web/__init__.py
secuscan/scanners/web/sast.py
secuscan/scanners/web/scanner.py
secuscan-1.1.3.dist-info/licenses/LICENSE
secuscan-1.1.3.dist-info/METADATA
secuscan-1.1.3.dist-info/WHEEL
secuscan-1.1.3.dist-info/entry_points.txt
secuscan-1.1.3.dist-info/top_level.txt
secuscan-1.1.3.dist-info/RECORD
