Metadata-Version: 2.4
Name: secuscan
Version: 1.1.3
Summary: A dual-platform static vulnerability scanner for Android and Web applications.
Author-email: SecuScan Team <secuscan7@gmail.com>
Classifier: Programming Language :: Python :: 3
Classifier: License :: OSI Approved :: MIT License
Requires-Python: >=3.9
License-File: LICENSE
Requires-Dist: click>=8.0.0
Requires-Dist: rich>=12.0.0
Requires-Dist: requests>=2.28.0
Requires-Dist: docker>=6.0.0
Requires-Dist: pyyaml>=6.0.0
Requires-Dist: bandit>=1.7.0
Requires-Dist: jinja2>=3.0.0
Dynamic: license-file
